safety_road_mapping/.env.example
safety_road_mapping/__init__.py
safety_road_mapping/__version__.py
safety_road_mapping/examples/how-to-use.ipynb
safety_road_mapping/examples/test_routes.ipynb
safety_road_mapping/extract_data/consolidate_data.ipynb
safety_road_mapping/extract_data/data/.gitignore
safety_road_mapping/extract_data/eda_accidents.ipynb
safety_road_mapping/extract_data/get_data.ipynb
safety_road_mapping/extract_data/treat_data_from_SP.ipynb
safety_road_mapping/extract_data/trechos.csv
safety_road_mapping/maps/final_map.html
safety_road_mapping/maps/final_map2.html
safety_road_mapping/maps/map_C. AGUDOS_Ambev S.A. - CDD Ribeirao Preto.html
safety_road_mapping/maps/map_C. ANÁPOLIS_Ambev S.A- CDD F. Brasilia.html
safety_road_mapping/maps/map_C. CAMAÇARI_CRBS S.A - CDD Salvador.html
safety_road_mapping/maps/map_C. JACAREÍ_Ambev S.A. - CDD Campinas.html
safety_road_mapping/maps/map_C. NOVA MINAS_CRBS S.A - CDL Santa Luzia.html
safety_road_mapping/maps/map_C. NOVA RIO_AMBEV S.A. - CDD VITÓRIA.html
safety_road_mapping/maps/map_C. NOVA RIO_CRBS S.A - CDD Niteroi.html
safety_road_mapping/maps/map_C. NOVA RIO_F. CDR Extrema-DC.html
safety_road_mapping/maps/map_C. PERNAMBUCO_Ambev S.A. - CDD Olinda.html
safety_road_mapping/maps/map_C. ÁGUAS CLARAS DO SUL_CRBS S.A - CDD Porto Alegre.html
safety_road_mapping/maps/teste_com_dados.html
safety_road_mapping/maps/teste_com_dados2.html
safety_road_mapping/safety.py
safety_road_mapping-0.1.7.dist-info/WHEEL
safety_road_mapping-0.1.7.dist-info/METADATA
safety_road_mapping-0.1.7.dist-info/RECORD
