Metadata-Version: 2.1
Name: safety-road-mapping
Version: 0.1.7
Summary: Module to generate a safety score for brazilian roads.
Home-page: https://github.com/cervejaria-ambev/safety_road_mapping
License: MIT
Keywords: geopy,safety,folium
Author: Gabriel Aparecido Fonseca
Requires-Python: >=3.8,<4.0
Classifier: Development Status :: 3 - Alpha
Classifier: License :: OSI Approved :: MIT License
Classifier: Operating System :: OS Independent
Classifier: Programming Language :: Python :: 3
Classifier: Programming Language :: Python :: 3.8
Classifier: Programming Language :: Python :: 3.9
Classifier: Topic :: Scientific/Engineering :: GIS
Classifier: Topic :: Software Development :: Libraries :: Python Modules
Requires-Dist: Unidecode (>=1.2.0,<2.0.0)
Requires-Dist: colour (>=0.1.5,<0.2.0)
Requires-Dist: folium (>=0.12.1,<0.13.0)
Requires-Dist: geopy (>=2.2.0,<3.0.0)
Requires-Dist: openrouteservice (>=2.3.3,<3.0.0)
Requires-Dist: pandas (>=1.3.2,<2.0.0)
Requires-Dist: patool (>=1.12,<2.0)
Requires-Dist: plotly (>=5.2.2,<6.0.0)
Requires-Dist: python-dotenv (>=0.19.0,<0.20.0)
Requires-Dist: typeguard (>=2.12.1,<3.0.0)
Requires-Dist: typing-extensions (>=3.10.0,<4.0.0)
Project-URL: Repository, https://github.com/cervejaria-ambev/safety_road_mapping
